eshpy/__init__.py
eshpy/data_processing.py
eshpy/layers.py
eshpy/learning.py
eshpy/net.py
eshpy-0.1.2.3.dist-info/METADATA
eshpy-0.1.2.3.dist-info/WHEEL
eshpy-0.1.2.3.dist-info/top_level.txt
eshpy-0.1.2.3.dist-info/RECORD
