Metadata-Version: 2.1
Name: eshpy
Version: 0.1.2.3
Summary: Deep Learning library based on PyTorch
Home-page: https://github.com/Eg0rSheremet0v/eshpy
Author: Egor Sheremetov
Author-email: georgesheremetov3.0@gmail.com
License: UNKNOWN
Platform: UNKNOWN
Classifier: Programming Language :: Python :: 3
Classifier: License :: OSI Approved :: Apache Software License
Classifier: Operating System :: OS Independent
